{"id": 41074, "wybug_id": "wooyun-2015-090021", "wybug_title": "某市地震局分站Sql注入和越权", "wybug_corp": "cncert国家互联网应急中心", "wybug_author": "天明", "wybug_date": "2015-01-06 12:58", "wybug_open_date": "2015-02-20 13:00", "wybug_type": "SQL注射漏洞", "wybug_level": "中", "wybug_rank_0": "10", "wybug_status": "已交由第三方合作机构(cncert国家互联网应急中心)处理", "wybug_from": "http://www.wooyun.org", "wybug_tags": ["数字类型注射"], "wybug_detail": "漏洞详情 披露状态：   \t\t\t\t\t\t\t\t\t2015-01-06：\t细节已通知厂商并且等待厂商处理中\t\t\t\t\t\t\t\t\t2015-01-11：\t厂商已经确认，细节仅向厂商公开\t\t\t\t\t\t\t\t\t2015-01-21：\t细节向核心白帽子及相关领域专家公开\t\t\t\t\t\t\t\t\t2015-01-31：\t细节向普通白帽子公开\t\t\t\t\t\t\t\t\t2015-02-10：\t细节向实习白帽子公开\t\t\t\t\t\t\t\t\t2015-02-20：\t细节向公众公开  简要描述： 某市地震局分站存在root权限的Sql注入和越权 详细说明：  上海地震局防震减灾信息化管理系统存在越权和root权限的SQl注入地址：http://220.196.57.132/\n\nsql注入：http://220.196.57.132/xcshtitle.php?id=741\n\n\n\n\n\n第二次读取速度太慢了，我就不读取了   漏洞证明：  上海地震局防震减灾信息化管理系统存在越权和root权限的SQl注入地址：http://220.196.57.132/\n\nsql注入：http://220.196.57.132/xcshtitle.php?id=741\n\n\n\n\n\n第二次读取速度太慢了，我就不读取了   修复方案：  RT   版权声明：转载请注明来源 天明@乌云\n ", "wybug_reply": "漏洞回应  厂商回应： 危害等级：高 漏洞Rank：11  确认时间：2015-01-11 10:32 厂商回复：   最新状态： 暂无  ", "replys": "漏洞评价：\n评论\n  \n\n\n", "wybug_level_fromcorp": "高", "wybug_rank_fromcorp": 11, "Ranks": null}