{"id": 36640, "wybug_id": "wooyun-2015-0101391", "wybug_title": "桂林电器科学研究院ftp未访问授权", "wybug_corp": "cncert国家互联网应急中心", "wybug_author": "无心、", "wybug_date": "2015-03-17 10:16", "wybug_open_date": "2015-05-04 17:24", "wybug_type": "未授权访问/权限绕过", "wybug_level": "中", "wybug_rank_0": "8", "wybug_status": "已交由第三方合作机构(cncert国家互联网应急中心)处理", "wybug_from": "http://www.wooyun.org", "wybug_tags": "", "wybug_detail": "漏洞详情 披露状态：   \t\t\t\t\t\t\t\t\t2015-03-17：\t细节已通知厂商并且等待厂商处理中\t\t\t\t\t\t\t\t\t2015-03-20：\t厂商已经确认，细节仅向厂商公开\t\t\t\t\t\t\t\t\t2015-03-30：\t细节向核心白帽子及相关领域专家公开\t\t\t\t\t\t\t\t\t2015-04-09：\t细节向普通白帽子公开\t\t\t\t\t\t\t\t\t2015-04-19：\t细节向实习白帽子公开\t\t\t\t\t\t\t\t\t2015-05-04：\t细节向公众公开  简要描述： 花舞花落泪，花哭花瓣飞。 花开为谁谢，花谢为谁悲。 蝴蝶为花醉，花却随风飞。 花凋花谢花无悔，人来人散人迷惘。 花榭花飞飞满天，红绡香断有谁怜？花开花落花无常，曲终曲散曲双亡. 详细说明：  ftp://202.103.209.125\n\nIP查询域名未果，准备放弃。\n\n软件上面显示个人名，想想，还是自己上去看看。\n\n孤单的一个软件在上面，就点击进去看看。\n\n\n\n我靠，好多东西啊，慢慢看看，看看能不能发现那个公司的。作为吃货，首先看看食堂啦：\n\n\n\n领导每餐才用18块，员工用20多，也是蛮不错的公司。再看看ftp的详情：\n\n\n\n看不懂。。。   漏洞证明：  终于在资料里面发现哪家公司的了：\n\n\n\n真是好找啊。。。。这个ftp里面好多私人性质东西。。。\n\n\n\n\n\n都是我喜欢的歌。。。   修复方案：     版权声明：转载请注明来源 无心、@乌云\n ", "wybug_reply": "漏洞回应  厂商回应： 危害等级：高 漏洞Rank：13  确认时间：2015-03-20 17:22 厂商回复： CNVD确认所述情况，已经转由CNCERT下发给分中心，由其后续协调网站管理单位处置。 最新状态： 暂无  ", "replys": "漏洞评价：\n评论\n  \n\n\n", "wybug_level_fromcorp": "高", "wybug_rank_fromcorp": 13, "Ranks": null}