{"id": 13769, "wybug_id": "wooyun-2013-018616", "wybug_title": "某火车站自助取票终端绕过", "wybug_corp": "12306", "wybug_author": "winT", "wybug_date": "2013-02-12 12:45", "wybug_open_date": "2013-03-29 12:46", "wybug_type": "未授权访问/权限绕过", "wybug_level": "低", "wybug_rank_0": "5", "wybug_status": "已交由第三方合作机构(cncert国家互联网应急中心)处理", "wybug_from": "http://www.wooyun.org", "wybug_tags": ["终端机安全", "未授权访问", "沙盒绕过"], "wybug_detail": "漏洞详情 披露状态：   \t\t\t\t\t\t\t\t\t2013-02-12：\t细节已通知厂商并且等待厂商处理中\t\t\t\t\t\t\t\t\t2013-02-16：\t厂商已经确认，细节仅向厂商公开\t\t\t\t\t\t\t\t\t2013-02-26：\t细节向核心白帽子及相关领域专家公开\t\t\t\t\t\t\t\t\t2013-03-08：\t细节向普通白帽子公开\t\t\t\t\t\t\t\t\t2013-03-18：\t细节向实习白帽子公开\t\t\t\t\t\t\t\t\t2013-03-29：\t细节向公众公开  简要描述： 终端绕过 可访问系统、内网渗透 详细说明：  长按屏幕任意位置，弹出Adobe Flash Player设置管理器，选择保密性设置高级选项卡，跳转入介绍Adobe Flash Player设置管理器页面...PS:某数字公司杀软无处不在...   漏洞证明：  \n\n\n\n   修复方案：     版权声明：转载请注明来源 winT@乌云\n ", "wybug_reply": "漏洞回应  厂商回应： 危害等级：低 漏洞Rank：3  确认时间：2013-02-16 23:14 厂商回复： CNVD确认漏洞情况，此类事件暂未列入处置流程。抱歉。rank 3 最新状态： 暂无  ", "replys": "漏洞评价：\n评论\n     2013-02-12 14:01 |    \t\t椰子 \t\t\t( 路人 |\t\t\t        Rank:5 漏洞数:1        )\t\t \n  mark    \n     2013-02-17 01:17 |    \t\ttpu01yzx \t\t\t( 实习白帽子  |\t\t\t        Rank:58 漏洞数:8        | test)\t\t \n  我比较惦记着是否因此可以免费买火车票    \n     2013-03-09 07:26 |    \t\t苏南同学 \t\t\t( 实习白帽子  |\t\t\t        Rank:41 漏洞数:5        | 苏南同学，就是苏南同学~~~)\t\t \n  我以为是可以打印别人的火车票呢    \n     2013-03-29 13:04 |    \t\tkindle \t\t\t( 实习白帽子  |\t\t\t        Rank:40 漏洞数:12        | hh)\t\t \n  北京南站。。。。    \n     2013-03-29 13:05 |    \t\tkindle \t\t\t( 实习白帽子  |\t\t\t        Rank:40 漏洞数:12        | hh)\t\t \n  打错，是北站。    \n     2013-03-29 13:05 |    \t\tkindle \t\t\t( 实习白帽子  |\t\t\t        Rank:40 漏洞数:12        | hh)\t\t \n  是西站。。反正就是军事博物馆那个    \n     2013-03-29 13:51 |    \t\tblrk \t\t\t( 实习白帽子  |\t\t\t        Rank:66 漏洞数:6        | 粪豆褶)\t\t \n  楼上自己玩的好欢乐啊，哈哈    \n     2013-03-29 17:00 |    \t\t店小弎 \t\t\t( 实习白帽子  |\t\t\t        Rank:93 漏洞数:13        | 关注web安全)\t\t \n  北京西站南广场的  已经玩过了    \n     2013-04-01 12:00 |    \t\ttSt \t\t\t( 路人 |\t\t\t        Rank:27 漏洞数:7        | 在开发里运维最强，运维里网络最强，网络里...)\t\t \n  昨天玩联通营业厅的点高级弹不出来啊~~~    \n     2013-04-01 16:17 |    \t\tkindle \t\t\t( 实习白帽子  |\t\t\t        Rank:40 漏洞数:12        | hh)\t\t \n  @tSt 你点一下帮助试试，右上角那个问号    \n     2013-04-01 23:24 |    \t\ttSt \t\t\t( 路人 |\t\t\t        Rank:27 漏洞数:7        | 在开发里运维最强，运维里网络最强，网络里...)\t\t \n  @kindle 下次试试   不过不办业务基本没空去啊    \n     2014-04-21 14:56 |    \t\t小贱人 \t\t\t( 路人 |\t\t\t        Rank:4 漏洞数:3        | 资深菜鸟，)\t\t \n  mark    \n  \n\n\n", "wybug_level_fromcorp": "低", "wybug_rank_fromcorp": 3, "Ranks": null}