{"id": 44756, "wybug_id": "wooyun-2015-098696", "wybug_title": "北京中科三方网络技术有限公司两站heartbleed未修补可登录账户", "wybug_corp": "北京中科三方网络技术有限公司", "wybug_author": "light", "wybug_date": "2015-02-28 18:07", "wybug_open_date": "2015-04-14 18:08", "wybug_type": "系统/服务补丁不及时", "wybug_level": "高", "wybug_rank_0": "18", "wybug_status": "厂商已经确认", "wybug_from": "http://www.wooyun.org", "wybug_tags": ["敏感信息泄露"], "wybug_detail": "漏洞详情 披露状态：   \t\t\t\t\t\t\t\t\t2015-02-28：\t细节已通知厂商并且等待厂商处理中\t\t\t\t\t\t\t\t\t2015-03-03：\t厂商已经确认，细节仅向厂商公开\t\t\t\t\t\t\t\t\t2015-03-13：\t细节向核心白帽子及相关领域专家公开\t\t\t\t\t\t\t\t\t2015-03-23：\t细节向普通白帽子公开\t\t\t\t\t\t\t\t\t2015-04-02：\t细节向实习白帽子公开\t\t\t\t\t\t\t\t\t2015-04-14：\t细节向公众公开  简要描述： 北京中科三方网络技术有限公司两站heartbleed未修补，导致大量用户明文密码泄露 详细说明：  https://next.sfn.cn/ 分站heartbleed漏洞未修补，导致大量用户明文密码泄露https://admin.sfn.cn   漏洞证明：  \n\n获取的账号可顺利登陆\n\n   修复方案：  升级openssl或打补丁   版权声明：转载请注明来源 light@乌云\n ", "wybug_reply": "漏洞回应  厂商回应： 危害等级：高 漏洞Rank：18  确认时间：2015-03-03 13:37 厂商回复： 已收到信息，我方会尽快处理 最新状态： 暂无  ", "replys": "漏洞评价：\n评论\n  \n\n\n", "wybug_level_fromcorp": "高", "wybug_rank_fromcorp": 18, "Ranks": null}