{"id": 78275, "wybug_id": "wooyun-2015-0160806", "wybug_title": "广州市团委管理系统账号密码泄露且众多账号都是弱口令/泄露敏感信息", "wybug_corp": "广东省信息安全测评中心", "wybug_author": "路人甲", "wybug_date": "2015-12-17 22:24", "wybug_open_date": "2015-12-22 22:26", "wybug_type": "敏感信息泄露", "wybug_level": "高", "wybug_rank_0": "10", "wybug_status": "已交由第三方合作机构(广东省信息安全测评中心)处理", "wybug_from": "http://www.wooyun.org", "wybug_tags": "", "wybug_detail": "漏洞详情 披露状态：   \t\t\t\t\t\t\t\t\t2015-12-17：\t细节已通知厂商并且等待厂商处理中\t\t\t\t\t\t\t\t\t2015-12-22：\t厂商已经主动忽略漏洞，细节向公众公开  简要描述： 广州市团委管理系统账号密码泄露且众多账号都是弱口令，泄露敏感信息 详细说明：  \n\n\n\n\n\n\n\n登录网站：http://**.**.**.**     记得不要带index.html账号：**.**.**.**.001.004.001密码：123456  同密码账号：**.**.**.**.008.002.001\t\t**.**.**.**.008.002.002\t\t\t**.**.**.**.008.002.003\t\t**.**.**.**.004.001.001\t\t\t**.**.**.**.004.002.001\t\t\t**.**.**.**.007.003.001\t\t\t**.**.**.**.001.004.001\t\t\t**.**.**.**.004.007.001\t\t\t**.**.**.**.004.001.002\t\t\t**.**.**.**.004.002.002\t\t\t**.**.**.**.007.003.002\t\t\t**.**.**.**.004.007.002\t\t\t**.**.**.**.001.001.003\t\t\t**.**.**.**.004.001.003\t\t\t**.**.**.**.001.002.003\t\t**.**.**.**.004.002.003\t\t\t**.**.**.**.007.003.003\t\t\t**.**.**.**.001.004.003\t\t\t**.**.**.**.004.007.003\t\t\t**.**.**.**.001.002.004\t\t\t**.**.**.**.007.003.004\t\t\t**.**.**.**.001.001.005\t\t\t**.**.**.**.007.003.005\t\t\t**.**.**.**.001.001.006\t        **.**.**.**.007.002.009   漏洞证明：  \n\n\n\n\n\n暴漏所有团委及所在具体位置\n\n\n\n 暴漏骨干个人具体信息   修复方案：     版权声明：转载请注明来源 路人甲@乌云\n ", "wybug_reply": "漏洞回应  厂商回应： 危害等级：无影响厂商忽略 忽略时间：2015-12-22 22:26 厂商回复：  最新状态： 暂无  ", "replys": "漏洞评价：\n评价\n  \n\n\n", "wybug_level_fromcorp": "无影响厂商忽略", "wybug_rank_fromcorp": 0, "Ranks": null}