{"id": 65022, "wybug_id": "wooyun-2013-020002", "wybug_title": "利海集团官网多个漏洞导致服务器沦陷", "wybug_corp": "利海集团", "wybug_author": "N1ghtBird", "wybug_date": "2013-03-13 13:51", "wybug_open_date": "2013-06-14 10:45", "wybug_type": "未授权访问/权限绕过", "wybug_level": "高", "wybug_rank_0": "10", "wybug_status": "未联系到厂商或者厂商积极忽略", "wybug_from": "http://www.wooyun.org", "wybug_tags": ["安全意识不足", "未授权访问", "用户敏感信息泄露", "认证设计不合理"], "wybug_detail": "漏洞详情 披露状态：   \t\t\t\t\t\t\t\t\t2013-03-13：\t积极联系厂商并且等待厂商认领中，细节不对外公开\t\t\t\t\t\t\t\t\t2013-06-14：\t厂商已经主动忽略漏洞，细节向公众公开  简要描述： 后台访问验证+上传+权限配置=沦陷 详细说明：  总之就是渗透..一些看起来不重要的小问题综合利用.扫到后台：\ngreen.lsea.com.cn/admin/default.aspx\n访问后发现属于某CMS系统早期版，根据通用漏洞fiddlerScript过滤js跳转绕过验证.后台Excel报表上传功能验证不严谨，改包上传成功.读Web.config得到mssql账号密码，is_srvrolemember('sysadmin')确认是SA权限，master.dbo.xp_cmdshell提权成功。   漏洞证明：  \n\n   修复方案：  你们比我懂..   版权声明：转载请注明来源 N1ghtBird@乌云\n ", "wybug_reply": "漏洞回应  厂商回应： 未能联系到厂商或者厂商积极拒绝  ", "replys": "漏洞评价：\n评论\n  \n\n\n", "wybug_level_fromcorp": "无影响厂商忽略", "wybug_rank_fromcorp": 0, "Ranks": null}