{"id": 17373, "wybug_id": "wooyun-2012-012705", "wybug_title": "sourceforge韩国节点被入侵，对天朝影响很大", "wybug_corp": "sourceforge", "wybug_author": "路人甲", "wybug_date": "2012-09-25 12:45", "wybug_open_date": "2012-09-25 12:45", "wybug_type": "成功的入侵事件", "wybug_level": "低", "wybug_rank_0": "3", "wybug_status": "未联系到厂商或者厂商积极忽略", "wybug_from": "http://www.wooyun.org", "wybug_tags": "", "wybug_detail": "漏洞详情 披露状态：   \t\t\t\t\t\t\t\t\t2012-09-25：\t积极联系厂商并且等待厂商认领中，细节不对外公开\t\t\t\t\t\t\t\t\t2012-09-25：\t厂商已经主动忽略漏洞，细节向公众公开  简要描述： 从微博上看到腾讯安全团队说sourceforge一些服务器被入侵，一些源码被植入后门，仔细研究了下，发现并非sourceforge被入侵，而是下面的韩国镜像节点提供商cdnetworks服务器存在问题 详细说明：  在sourceforge上下载源码时，会根据网络情况自动选择镜像节点下载，由于我国没有镜像服务器，所以会从最近的韩国的节点上下载，这次腾讯也发现有phpMyadmin源码被植入了后门的情况，我们经过分析发现其他的节点均不存在问题，只有韩国的cdnetworks提供的某些镜像中才存在问题   漏洞证明：  自动选择的韩国节点上下载phpMyadmin源码会发现存在后门\nhttp://cdnetworks-kr-1.dl.sourceforge.net/project/phpmyadmin/phpMyAdmin/3.5.2.2/phpMyAdmin-3.5.2.2-all-languages.zip\n\n\n时间比较早了，在8月份的时候应该就被更改过了，近期下载过pma的要小心了！但是并非所有的镜像都有问题，通过选择其他节点\n\n验证后并非都有后门，而我们自动选择的却恰恰是有后门的源码！有后门的也正是cdnetworks这个韩国节点   修复方案：  韩国的安全我们知道一直都不是特别好的，希望韩国提升自身安全性，不要影响我们天朝，另外天朝也需要自力更生，建立个镜像节点吧，腾讯建立一个就很赞！   版权声明：转载请注明来源 路人甲@乌云\n ", "wybug_reply": "漏洞回应  厂商回应： 未能联系到厂商或者厂商积极拒绝  ", "replys": "漏洞评价：\n评论\n     2012-09-25 12:46 |    \t\txsser  \t\t\t( 普通白帽子  |\t\t\t        Rank:254 漏洞数:18        | 当我又回首一切,这个世界会好吗?)\t\t \n  棒子是不是故意的啊？？    \n     2012-09-25 12:49 |    \t\tgainover  \t\t\t( 核心白帽子 |\t\t\t        Rank:1710 漏洞数:93        | PKAV技术宅社区! -- gainover| 工具猫网络-...)\t\t \n  难说～～    \n     2012-09-25 12:50 |    \t\tNimda \t\t\t( 路人 |\t\t\t        Rank:13 漏洞数:3        | 人的欲望就是一个超级大坑，永远也填不满。...)\t\t \n  我是来看标题的    \n     2012-09-25 12:57 |    \t\tXhm1n9 \t\t\t( 实习白帽子  |\t\t\t        Rank:57 漏洞数:13        | bug)\t\t \n  关注一下    \n     2012-09-25 13:05 |    \t\thorseluke \t\t\t( 普通白帽子  |\t\t\t        Rank:116 漏洞数:18        | Realize the dream in earnest.)\t\t \n  神奇的路人甲...    \n     2012-09-25 13:09 |    \t\t小禾吉 \t\t\t( 路人 |\t\t\t        Rank:0 漏洞数:1        | 宇宙的目的很可能和人类没有关系，宇宙很可...)\t\t \n  要粗大事了？    \n     2012-09-25 13:18 |    \t\t混世魔王 \t\t\t( 路人 |\t\t\t        Rank:26 漏洞数:5        | 欢迎友情链接http://26836659.blogcn.com)\t\t \n  这不算什么。sourceforge 的主美国站，我都日进去了。只是没公布而已。    \n     2012-09-25 13:28 |    \t\tMujj \t\t\t( 实习白帽子  |\t\t\t        Rank:58 漏洞数:4        | IDC商)\t\t \n  @混世魔王 哦，炫耀党    \n     2012-09-25 13:30 |    \t\tSpy4man \t\t\t( 路人 |\t\t\t        Rank:0 漏洞数:1        | 职业运维师..)\t\t \n  @混世魔王 咳咳...    \n     2012-09-25 14:10 |    \t\tHuGtion \t\t\t( 实习白帽子  |\t\t\t        Rank:70 漏洞数:10        | 学习安全技术。)\t\t \n  话说 SF 的开源精神灰常的强大\"SourceForge空间可任意查看服务器文件导致密码泄露事件1、SF空间的此“漏洞”由来已久。查了一下网上的资料，2010-08-18有网站就公布了“SourceForge某站点存在任意读取本地文件漏洞”。2、漏洞类型：任意文件遍历/下载。由于sourceForge使用nfs集中管理所有网站文件，可能导致产生大量的敏感信息泄露。3、当然后来SF空间修补了这个漏洞，但是SourceForge空间可查看任意文件一直没有改变，因为官方称SourceForge是一个开源免费平台。4、所有的放在SF空间上的程序和文件都是可以自由免费下载的。这一开源分享的“精神”可佳，可惜如果我们将一些敏感的信息的文件放在SF空间上就有可能遭受损失了。5、只要改变路径就能查看一切项目的任何文件，就算此项目不是自己创建的，这意味着将网站部署于SourceForge，任何其他用户都能对你的数据库进行操作。6、而且config文件里的密码如果是你常用密码的话... 某些“好奇之士” 难道不会去尝试去登录一下你的Godaddy空间或者其它的平台吗？ \"    \n     2012-09-25 14:11 |    \t\txsser  \t\t\t( 普通白帽子  |\t\t\t        Rank:254 漏洞数:18        | 当我又回首一切,这个世界会好吗?)\t\t \n  @HuGtion 问题是这次的问题不再Sourceforge 而在于韩国节点    \n     2012-09-25 14:16 |    \t\tj14n \t\t\t( 普通白帽子  |\t\t\t        Rank:114 漏洞数:23        | 我是一只小小小小鸟....)\t\t \n  楼主是雷锋啊。。    \n     2012-09-25 15:01 |    \t\t神刀 \t\t\t( 路人 |\t\t\t        Rank:23 漏洞数:3        | www.shellsec.com内射那么牛，虾米没妹子？)\t\t \n  我是看标题进来的    \n     2012-09-25 15:25 |    \t\t蟋蟀哥哥 \t\t\t( 普通白帽子  |\t\t\t        Rank:363 漏洞数:57        | 巴蜀人士,80后宅男,自学成才,天朝教育失败...)\t\t \n  自建结点??你说备案怎么办呢。。国人都被难死了，别说老外了    \n     2012-09-25 15:27 |    \t\t蟋蟀哥哥 \t\t\t( 普通白帽子  |\t\t\t        Rank:363 漏洞数:57        | 巴蜀人士,80后宅男,自学成才,天朝教育失败...)\t\t \n  这次玩大了。。这个漏洞。。受影响估计有很多人的。。包括我自己的多个站点都可能存在这个问题。。自查去了    \n     2012-09-25 16:36 |    \t\tCHForce \t\t\t( 路人 |\t\t\t        Rank:0 漏洞数:1        | 路过不代表我冷漠，走路不代表没有马)\t\t \n  哈哈。我是用源代码，都是学习，很少直接用的    \n     2012-09-25 22:06 |    \t\tNimda \t\t\t( 路人 |\t\t\t        Rank:13 漏洞数:3        | 人的欲望就是一个超级大坑，永远也填不满。...)\t\t \n  刚下了个pma，确实如洞主所说，不过为毛插马的货没藏在其他文件里？。。。纳闷球中    \n     2012-09-26 00:05 |    \t\t北北 \t\t\t( 路人 |\t\t\t        Rank:25 漏洞数:5        | 广告位招租。有阿里、万网的漏洞私信给我有...)\t\t \n  之前都把SF墙了，咋还可能国内放节点~ 你看看那个牛X的一句话，目测国人干的。    \n     2012-09-26 13:15 |    \t\tMujj \t\t\t( 实习白帽子  |\t\t\t        Rank:58 漏洞数:4        | IDC商)\t\t \n  @蟋蟀哥哥 蛋疼了吧    \n     2012-09-26 13:35 |    \t\t蟋蟀哥哥 \t\t\t( 普通白帽子  |\t\t\t        Rank:363 漏洞数:57        | 巴蜀人士,80后宅男,自学成才,天朝教育失败...)\t\t \n  @Mujj 自查了的。。没有中招    \n  \n\n\n", "wybug_level_fromcorp": "无影响厂商忽略", "wybug_rank_fromcorp": 0, "Ranks": null}