{"id": 16533, "wybug_id": "wooyun-2015-0117516", "wybug_title": "支付行业安全之拉卡拉另一个系统大量账户体系控制不严导致Getshell再入内网(涉及大量员工\\财务\\账务等内部敏感信息)", "wybug_corp": "拉卡拉网络技术有限公司", "wybug_author": "管管侠", "wybug_date": "2015-06-01 15:46", "wybug_open_date": "2015-07-17 09:24", "wybug_type": "账户体系控制不严", "wybug_level": "高", "wybug_rank_0": "15", "wybug_status": "厂商已经确认", "wybug_from": "http://www.wooyun.org", "wybug_tags": "", "wybug_detail": "漏洞详情 披露状态：   \t\t\t\t\t\t\t\t\t2015-06-01：\t细节已通知厂商并且等待厂商处理中\t\t\t\t\t\t\t\t\t2015-06-02：\t厂商已经确认，细节仅向厂商公开\t\t\t\t\t\t\t\t\t2015-06-12：\t细节向核心白帽子及相关领域专家公开\t\t\t\t\t\t\t\t\t2015-06-22：\t细节向普通白帽子公开\t\t\t\t\t\t\t\t\t2015-07-02：\t细节向实习白帽子公开\t\t\t\t\t\t\t\t\t2015-07-17：\t细节向公众公开  简要描述： 连夜发一个，厂商没确认，估计是忘了，我再提醒下 详细说明：  http://admin.lakalaec.com/index可以爆破，来吧\n\n十几个账号，仅测试了123456密码   漏洞证明：  \n\n\n\n\n\n\n\n可以反弹个代理继续检测内网，算了，点到为止这是shell：http://admin.lakalaec.com/tempImg/297/mainImg/b4483c21-0e37-48d8-a396-e260a0a4ff55.jsp   修复方案：  哈，你们是个全国性的大公司点到为止！！！   版权声明：转载请注明来源 管管侠@乌云\n ", "wybug_reply": "漏洞回应  厂商回应： 危害等级：中 漏洞Rank：5  确认时间：2015-06-02 09:22 厂商回复： 正在修复。 最新状态： 暂无  ", "replys": "漏洞评价：\n评论\n     2015-06-01 16:15 |    \t\t糖剩七颗 \t\t\t( 普通白帽子  |\t\t\t        Rank:430 漏洞数:61        | 天涯何处无屌丝)\t\t \n  目测又是人员邮箱    \n     2015-06-01 16:25 |    \t\t管管侠 \t\t\t( 核心白帽子 |\t\t\t        Rank:1368 漏洞数:108        | 休息几日，让你们先装会！！！)\t\t \n  @糖剩七颗 你测错了，不是邮箱    \n     2015-06-01 17:09 |    \t\t牛 小 帅 \t\t\t( 普通白帽子  |\t\t\t        Rank:363 漏洞数:84        | [code]心若没有栖息的地方，走到哪里都是在...)\t\t \n  这个会不会打雷,我小学生来凑热闹    \n     2015-06-01 18:13 |    \t\t蛋蛋侠 \t\t\t( 普通白帽子  |\t\t\t        Rank:100 漏洞数:13        | 我是一只蛋)\t\t \n  @浩天 我wb转账，什么时候能到账？一直在冻结中。    \n     2015-06-03 11:50 |    \t\tr00tgrok \t\t\t( 路人 |\t\t\t        还没有发布任何漏洞        | 上帝死了)\t\t \n  代码都被脱下来了，只给5个rank    \n     2015-06-03 11:56 |    \t\t牛 小 帅 \t\t\t( 普通白帽子  |\t\t\t        Rank:363 漏洞数:84        | [code]心若没有栖息的地方，走到哪里都是在...)\t\t \n  @浩天 帮我审核    \n     2015-07-18 01:04 |    \t\t北丐 \t\t\t( 普通白帽子  |\t\t\t        Rank:104 漏洞数:20        | )\t\t \n  @r00tgrok 看样子还得让管管侠继续撸他们 才会给高rank    \n  \n\n\n", "wybug_level_fromcorp": "中", "wybug_rank_fromcorp": 5, "Ranks": null}