{"id": 25568, "wybug_id": "wooyun-2015-0131061", "wybug_title": "三国杀BUG反馈可越权修改全站反馈帖子和官方公告", "wybug_corp": "边锋网络", "wybug_author": "小龙", "wybug_date": "2015-08-03 11:21", "wybug_open_date": "2015-09-17 11:50", "wybug_type": "设计缺陷/逻辑错误", "wybug_level": "高", "wybug_rank_0": "20", "wybug_status": "厂商已经确认", "wybug_from": "http://www.wooyun.org", "wybug_tags": ["设计缺陷", "设计不当"], "wybug_detail": "漏洞详情 披露状态：   \t\t\t\t\t\t\t\t\t2015-08-03：\t细节已通知厂商并且等待厂商处理中\t\t\t\t\t\t\t\t\t2015-08-03：\t厂商已经确认，细节仅向厂商公开\t\t\t\t\t\t\t\t\t2015-08-13：\t细节向核心白帽子及相关领域专家公开\t\t\t\t\t\t\t\t\t2015-08-23：\t细节向普通白帽子公开\t\t\t\t\t\t\t\t\t2015-09-02：\t细节向实习白帽子公开\t\t\t\t\t\t\t\t\t2015-09-17：\t细节向公众公开  简要描述： 20 详细说明：  \n\n   漏洞证明：  \nhttp://bug.sanguosha.com/?mod=view&id=7870官方公告也是这个：http://bug.sanguosha.com/?mod=announce&id=55\n   修复方案：  加个token啊。。   版权声明：转载请注明来源 小龙@乌云\n ", "wybug_reply": "漏洞回应  厂商回应： 危害等级：低 漏洞Rank：5  确认时间：2015-08-03 11:49 厂商回复： 谢谢小龙的漏洞，问题已着手处理。 最新状态： 2015-08-03：经代码复查确认帖子是可修改，但公告不可修改。  ", "replys": "漏洞评价：\n评论\n     2015-08-03 12:27 |    \t\tMr.R \t\t\t( 实习白帽子  |\t\t\t        Rank:52 漏洞数:14        | 求大神带我飞 qq2584110147)\t\t \n  三国杀，，，，，，还能不能愉快的玩耍了    \n     2015-08-03 12:39 |    \t\t小龙 \t\t\t( 普通白帽子  |\t\t\t        Rank:1208 漏洞数:316        | 乌云有着这么一群人，在乌云学技术，去某数...)\t\t \n  @Mr.R  或许还能！    \n     2015-08-03 13:13 |    \t\t小龙 \t\t\t( 普通白帽子  |\t\t\t        Rank:1208 漏洞数:316        | 乌云有着这么一群人，在乌云学技术，去某数...)\t\t \n  您好@边锋网络  真的会发吗？- -您发布的漏洞 三国杀BUG反馈可越权修改全站反馈帖子和官方公告 被厂商 边锋网络 确认，因为此厂商希望获得您的联系方式以便发送小礼物。是否接受并发送联系方式给此厂商? 接受    \n  \n\n\n", "wybug_level_fromcorp": "低", "wybug_rank_fromcorp": 5, "Ranks": null}