{"id": 17993, "wybug_id": "wooyun-2012-09662", "wybug_title": "QQ隐私设置绕过漏洞", "wybug_corp": "腾讯", "wybug_author": "leo108", "wybug_date": "2012-07-14 23:42", "wybug_open_date": "2012-08-28 23:43", "wybug_type": "设计缺陷/逻辑错误", "wybug_level": "中", "wybug_rank_0": "10", "wybug_status": "厂商已经确认", "wybug_from": "http://www.wooyun.org", "wybug_tags": "", "wybug_detail": "漏洞详情 披露状态：   \t\t\t\t\t\t\t\t\t2012-07-14：\t细节已通知厂商并且等待厂商处理中\t\t\t\t\t\t\t\t\t2012-07-16：\t厂商已经确认，细节仅向厂商公开\t\t\t\t\t\t\t\t\t2012-07-26：\t细节向核心白帽子及相关领域专家公开\t\t\t\t\t\t\t\t\t2012-08-05：\t细节向普通白帽子公开\t\t\t\t\t\t\t\t\t2012-08-15：\t细节向实习白帽子公开\t\t\t\t\t\t\t\t\t2012-08-28：\t细节向公众公开  简要描述： 能查看到性别、城市、年龄和星座这几项，对社工是很有帮助的资料。即使是在“系统设置”→“隐私设置”中，将各项资料的权限设置为仅自己可见，仍可以查看。 详细说明：  主要问题出在3GQQ的家园，利用方法如下：登录http://w.159.com/，输入网址http://3g.qq.com点击QQ，然后登录任意QQ帐号，登录成功之后点击最下方的“家园”这个时候WAP浏览器的地址应该是类似http://house60.3g.qq.com/g/s?sid=XXXXXXXXXXXXX&aid=home_self&g_f=9334的URL我们需要的就是sid的值，记录下来，假设是XXXXXXXXXXXXX这时候只要在wap浏览器中访问http://house60.3g.qq.com/g/profile/others_profile.jsp?from=visit&sid=XXXXXXXXXXXXX&u=目标用户QQ号&guest=true&g_ut=1即可获得对方资料   漏洞证明：  \n\n\n\n随便挑了两个号   修复方案：  检查权限……   版权声明：转载请注明来源 leo108@乌云\n ", "wybug_reply": "漏洞回应  厂商回应： 危害等级：低 漏洞Rank：1  确认时间：2012-07-16 11:39 厂商回复： 谢谢反馈，这属于逻辑设计缺陷，我们正在跟进处理。 最新状态： 暂无  ", "replys": "漏洞评价：\n评论\n     2012-07-14 23:46 |    \t\tpx1624 \t\t\t( 普通白帽子  |\t\t\t        Rank:1036 漏洞数:175        | px1624)\t\t \n  我估计会呗忽略掉，我上次发的可以直接看到真实姓名和头像的都直接被忽略了。。。    \n     2012-07-15 11:36 |    \t\tcnhello \t\t\t( 路人 |\t\t\t        Rank:0 漏洞数:1        | 小菜一枚，学习中。。。)\t\t \n  这个大牛不会填写的，同意楼上。。。    \n     2012-07-15 12:19 |    \t\t鬼魅羊羔 \t\t\t( 普通白帽子  |\t\t\t        Rank:299 漏洞数:42        | (#‵′)凸(#‵′)凸(#‵′)凸(#‵′)凸(#‵...)\t\t \n  坐等忽略……    \n  \n\n\n", "wybug_level_fromcorp": "低", "wybug_rank_fromcorp": 1, "Ranks": null}