{"id": 72804, "wybug_id": "wooyun-2015-0158336", "wybug_title": "银泰商业某系统设计缺陷导致近6W供应商财务信息泄漏\\任意操作任意商户\\任意文件上传", "wybug_corp": "银泰商业集团", "wybug_author": "幻老头儿", "wybug_date": "2015-12-04 18:25", "wybug_open_date": "2016-01-21 09:20", "wybug_type": "未授权访问/权限绕过", "wybug_level": "高", "wybug_rank_0": "20", "wybug_status": "厂商已经确认", "wybug_from": "http://www.wooyun.org", "wybug_tags": ["敏感接口未加权限认证"], "wybug_detail": "漏洞详情 披露状态：   \t\t\t\t\t\t\t\t\t2015-12-04：\t细节已通知厂商并且等待厂商处理中\t\t\t\t\t\t\t\t\t2015-12-07：\t厂商已经确认，细节仅向厂商公开\t\t\t\t\t\t\t\t\t2015-12-17：\t细节向核心白帽子及相关领域专家公开\t\t\t\t\t\t\t\t\t2015-12-27：\t细节向普通白帽子公开\t\t\t\t\t\t\t\t\t2016-01-06：\t细节向实习白帽子公开\t\t\t\t\t\t\t\t\t2016-01-21：\t细节向公众公开  简要描述： rt 详细说明：  http://122.224.218.142:7070/supplier/jsp/index.jsp银泰百货供应商网上对账平台\n\n任意用户名字，任意密码返回包，改成true\n\n里面有关于i融平台，下载说明的pdf\n\n里面有注册步骤说明，\n\n跟着填写对应信息，\n\n成功注册了一个帐号\n\n   漏洞证明：  i融平台地址http://irou.intime.com.cn:8380/supplier/jsp/main.jsp\n\n对应功能在基础信息查看时，修改商户id，就是这个修改商户id，造成了可以操作任意商户账户\n\n先看看商户的基础信息\n\n\n\n\n\n\n\n\n\n59000多商户的信息，利用id修改，可越权操作59000多商户的账户供应商月度对账\n\n\n\n\n\n\n\n\n\n供应商销售对账\n\n\n\n\n\n当日销售对账\n\n融资申请处，任意文件上传\n\n\n\n\n\n可以提前结款\n\n\n\n   修复方案：  权限控制。   版权声明：转载请注明来源 幻老头儿@乌云\n ", "wybug_reply": "漏洞回应  厂商回应： 危害等级：高 漏洞Rank：12  确认时间：2015-12-07 09:11 厂商回复： 十分感谢 幻老头儿 提交的漏洞，感谢广大白帽子对网络安全做出的积极贡献。我司会尽快处理 最新状态： 暂无  ", "replys": "漏洞评价：\n评价\n  \n\n\n", "wybug_level_fromcorp": "高", "wybug_rank_fromcorp": 12, "Ranks": null}