{"id": 25323, "wybug_id": "wooyun-2015-0131885", "wybug_title": "Q房网看房记录一览无余", "wybug_corp": "qfang.com", "wybug_author": "im503", "wybug_date": "2015-08-10 17:03", "wybug_open_date": "2015-08-15 17:04", "wybug_type": "重要敏感信息泄露", "wybug_level": "中", "wybug_rank_0": "8", "wybug_status": "漏洞已经通知厂商但是厂商忽略漏洞", "wybug_from": "http://www.wooyun.org", "wybug_tags": ["目录遍历", "敏感信息泄露", "默认配置不当"], "wybug_detail": "漏洞详情 披露状态：   \t\t\t\t\t\t\t\t\t2015-08-10：\t细节已通知厂商并且等待厂商处理中\t\t\t\t\t\t\t\t\t2015-08-15：\t厂商已经主动忽略漏洞，细节向公众公开  简要描述：  详细说明：  各种看房记录..任意浏览.http://58.61.160.7:8080/    漏洞证明：  \n[ ]\tqfang_20140630.zip\t30-Jun-2014 01:06 \t471M\t [ ]\tqfang_20140707.zip\t07-Jul-2014 01:06 \t454M\t [ ]\tqfang_20140714.zip\t14-Jul-2014 01:07 \t488M\t [ ]\tqfang_20140721.zip\t21-Jul-2014 01:06 \t480M\t [ ]\tqfang_20140728.zip\t28-Jul-2014 01:06 \t478M\t [ ]\tqfang_20140804.zip\t04-Aug-2014 01:07 \t553M\t [ ]\tqfang_20140811.zip\t11-Aug-2014 01:09 \t646M\t [ ]\tqfang_20140818.zip\t18-Aug-2014 01:10 \t701M\t [ ]\tqfang_20140825.zip\t25-Aug-2014 01:12 \t725M\t [ ]\tqfang_20140901.zip\t01-Sep-2014 01:08 \t664M\t [ ]\tqfang_20140908.zip\t08-Sep-2014 01:09 \t713M\t [ ]\tqfang_20140915.zip\t15-Sep-2014 01:05 \t517M\t [ ]\tqfang_20140922.zip\t22-Sep-2014 01:03 \t387M\t [ ]\tqfang_20140929.zip\t29-Sep-2014 01:05 \t492M\t [ ]\tqfang_20141006.zip\t06-Oct-2014 01:03 \t359M\t [ ]\tqfang_20141020.zip\t20-Oct-2014 01:04 \t415M\t [ ]\tqfang_20141027.zip\t27-Oct-2014 01:04 \t473M\t [ ]\tqfang_20141103.zip\t03-Nov-2014 01:06 \t533M\t [ ]\tqfang_20141110.zip\t10-Nov-2014 01:05 \t499M\t [ ]\tqfang_20141117.zip\t17-Nov-2014 01:04 \t483M\t [ ]\tqfang_20141124.zip\t24-Nov-2014 01:06 \t532M\t [ ]\tqfang_20141201.zip\t01-Dec-2014 01:05 \t487M\t [ ]\tqfang_20141208.zip\t08-Dec-2014 01:05 \t479M\t [ ]\tqfang_20141215.zip\t15-Dec-2014 01:05 \t489M\t [ ]\tqfang_20141222.zip\t22-Dec-2014 01:06 \t495M\t [ ]\tqfang_20141229.zip\t29-Dec-2014 01:05 \t483M\t [ ]\tqfang_20150105.zip\t05-Jan-2015 01:05 \t468M\t [ ]\tqfang_20150112.zip\t12-Jan-2015 01:05 \t489M\t [DIR]\tqfang_20150112/\t13-Jan-2015 10:45 \t- \t [ ]\tqfang_20150119.zip\t19-Jan-2015 01:06 \t504M\t [ ]\tqfang_20150126.zip\t26-Jan-2015 01:05 \t493M\t [ ]\tqfang_20150202.zip\t02-Feb-2015 01:04 \t450M\t [ ]\tqfang_20150209.zip\t09-Feb-2015 01:04 \t387M\t [ ]\tqfang_20150216.zip\t16-Feb-2015 01:03 \t321M\t [ ]\tqfang_20150223.zip\t23-Feb-2015 01:02 \t204M\t [ ]\tqfang_20150302.zip\t02-Mar-2015 01:03 \t397M\t [ ]\tqfang_20150309.zip\t09-Mar-2015 01:04 \t482M\t [ ]\tqfang_20150316.zip\t16-Mar-2015 01:04 \t391M\t [ ]\tqfang_20150323.zip\t23-Mar-2015 01:05 \t425M\t [ ]\tqfang_20150330.zip\t30-Mar-2015 01:05 \t505M\t [ ]\tqfang_20150406.zip\t06-Apr-2015 01:04 \t382M\t [ ]\tqfang_20150413.zip\t13-Apr-2015 01:02 \t223M\t [ ]\tqfang_20150420.zip\t20-Apr-2015 01:03 \t308M\t [ ]\tqfang_20150427.zip\t27-Apr-2015 01:03 \t335M\t [ ]\tqfang_20150504.zip\t04-May-2015 01:04 \t365M\t [ ]\tqfang_20150511.zip\t11-May-2015 01:05 \t425M\t [ ]\tqfang_20150518.zip\t18-May-2015 01:05 \t445M\t [ ]\tqfang_20150525.zip\t25-May-2015 01:05 \t430M\t [ ]\tqfang_20150601.zip\t01-Jun-2015 01:05 \t429M\t [ ]\tqfang_20150608.zip\t08-Jun-2015 01:05 \t470M\t [ ]\tqfang_20150615.zip\t15-Jun-2015 01:06 \t482M\t [ ]\tqfang_20150622.zip\t22-Jun-2015 01:05 \t415M\t [ ]\tqfang_20150629.zip\t29-Jun-2015 01:04 \t298M\t [ ]\tqfang_20150706.zip\t06-Jul-2015 01:03 \t301M\t [ ]\tqfang_20150713.zip\t13-Jul-2015 01:04 \t329M\t [ ]\tqfang_20150720.zip\t20-Jul-2015 01:04 \t339M\t [ ]\tqfang_20150727.zip\t27-Jul-2015 01:03 \t294M\t [ ]\tqfang_20150803.zip\t03-Aug-2015 01:01 \t98M\n   修复方案：  目录权限控制下，别直接777..   版权声明：转载请注明来源 im503@乌云\n ", "wybug_reply": "漏洞回应  厂商回应： 危害等级：无影响厂商忽略 忽略时间：2015-08-15 17:04 厂商回复：  漏洞Rank：2  (WooYun评价) 最新状态： 暂无  ", "replys": "漏洞评价：\n评论\n  \n\n\n", "wybug_level_fromcorp": "无影响厂商忽略", "wybug_rank_fromcorp": 0, "Ranks": null}