{"id": 48964, "wybug_id": "wooyun-2014-080964", "wybug_title": "新浪微博某处小功能存在CSRF漏洞（可修改用户微博某元素）", "wybug_corp": "新浪微博", "wybug_author": "孤独雪狼", "wybug_date": "2014-10-27 15:02", "wybug_open_date": "2014-12-11 15:04", "wybug_type": "CSRF", "wybug_level": "低", "wybug_rank_0": "5", "wybug_status": "厂商已经确认", "wybug_from": "http://www.wooyun.org", "wybug_tags": "", "wybug_detail": "漏洞详情 披露状态：   \t\t\t\t\t\t\t\t\t2014-10-27：\t细节已通知厂商并且等待厂商处理中\t\t\t\t\t\t\t\t\t2014-10-27：\t厂商已经确认，细节仅向厂商公开\t\t\t\t\t\t\t\t\t2014-11-06：\t细节向核心白帽子及相关领域专家公开\t\t\t\t\t\t\t\t\t2014-11-16：\t细节向普通白帽子公开\t\t\t\t\t\t\t\t\t2014-11-26：\t细节向实习白帽子公开\t\t\t\t\t\t\t\t\t2014-12-11：\t细节向公众公开  简要描述： 设计缺陷，问题不大，但如果做推广某个东西的话还是不错的。。。比如说****** 详细说明：  新版微博出了一个小功能（类似QQ空间一样），就是可以设置背景音乐。通过抓包后得知背景音乐某首歌的URL为：\nhttp://ting.weibo.com/music/weidanmobile/add?sid=2858931&gid=defaultid&key=f10aba96cdedec5df88cdaf6371d9ebf&token=5e04af60a57bc0b130ac9550f879b86e&plat=pc\n这里sid为这首歌的ID 后面token我理解为都是这首歌的。。直接点击上面的URL就可以看到在你个人页面左边有个背景音乐了：\n\n   漏洞证明：  \n\n\n\n   修复方案：     版权声明：转载请注明来源 孤独雪狼@乌云\n ", "wybug_reply": "漏洞回应  厂商回应： 危害等级：低 漏洞Rank：2  确认时间：2014-10-27 17:18 厂商回复： 感谢关注新浪安全，反馈的问题正在修复。 最新状态： 暂无  ", "replys": "漏洞评价：\n评论\n     2014-10-27 15:15 |    \t\t番茄炒蛋 \t\t\t( 普通白帽子  |\t\t\t        Rank:106 漏洞数:31        | test)\t\t \n  你又调皮了    \n     2014-10-27 15:15 |    \t\tpx1624 \t\t\t( 普通白帽子  |\t\t\t        Rank:1036 漏洞数:175        | px1624)\t\t \n  雪狼你这么叼，小胖胖知道么    \n     2014-10-27 15:16 |    \t\t番茄炒蛋 \t\t\t( 普通白帽子  |\t\t\t        Rank:106 漏洞数:31        | test)\t\t \n  @px1624 他媳妇肯定是知道的    \n     2014-10-27 15:25 |    \t\t孤独雪狼 \t\t\t( 普通白帽子  |\t\t\t        Rank:710 漏洞数:145        | 七夕手机被偷，这坑爹的七夕啊 。。。。)\t\t \n  @px1624 - -你妹    \n     2014-10-27 18:03 |    \t\t小威 \t\t\t( 普通白帽子  |\t\t\t        Rank:492 漏洞数:76        | 活到老，学到老!)\t\t \n  @孤独雪狼 小胖胖这是激情四射~    \n     2014-11-17 09:17 |    \t\t乐乐、 \t\t\t( 普通白帽子  |\t\t\t        Rank:853 漏洞数:189        )\t\t \n  ... 等等  这啥意思    \n  \n\n\n", "wybug_level_fromcorp": "低", "wybug_rank_fromcorp": 2, "Ranks": null}