{"id": 27974, "wybug_id": "wooyun-2015-0123933", "wybug_title": "医护网心脏流血漏洞导致用户数据泄漏", "wybug_corp": "医护网", "wybug_author": "arnoxia", "wybug_date": "2015-07-01 17:13", "wybug_open_date": "2015-08-15 17:14", "wybug_type": "系统/服务补丁不及时", "wybug_level": "高", "wybug_rank_0": "15", "wybug_status": "未联系到厂商或者厂商积极忽略", "wybug_from": "http://www.wooyun.org", "wybug_tags": ["漏洞"], "wybug_detail": "漏洞详情 披露状态：   \t\t\t\t\t\t\t\t\t2015-07-01：\t积极联系厂商并且等待厂商认领中，细节不对外公开\t\t\t\t\t\t\t\t\t2015-08-15：\t厂商已经主动忽略漏洞，细节向公众公开  简要描述： 医护网的ssl未对Heartbleed漏洞及时添加补丁，导致可以通过脚本爆出用户cookie以及用户id，从而导致用户数据泄漏 详细说明：  医护网：www.yihu.com\n\n通过Heartbleed脚本可以发现有漏洞，并且可以爆出数据：\n\n\n\n然后在医护网注册帐号，并替换cookie:\n\n成功替换用户，并看到敏感数据：\n\n\n\n如果通过自动话工具，可以爆出大量用户数据，还包括用户挂号信息，十分有用   漏洞证明：  \n\n\n\n\n\n\n\n   修复方案：  更新ssl版本   版权声明：转载请注明来源 arnoxia@乌云\n ", "wybug_reply": "漏洞回应  厂商回应： 未能联系到厂商或者厂商积极拒绝  ", "replys": "漏洞评价：\n评论\n     2015-07-15 22:37 |    \t\tarnoxia \t\t\t( 路人 |\t\t\t        Rank:6 漏洞数:4        | 一只菜鸟，正要飞)\t\t \n  @福建健康之路信息技术有限公司 快来确认吧    \n     2015-07-15 22:40 |    \t\tarnoxia \t\t\t( 路人 |\t\t\t        Rank:6 漏洞数:4        | 一只菜鸟，正要飞)\t\t \n  @疯狗 厂商福建健康之路信息技术有限公司已经注册    \n  \n\n\n", "wybug_level_fromcorp": "无影响厂商忽略", "wybug_rank_fromcorp": 0, "Ranks": null}